MANIFEST.in
README.rst
setup.py
pypartypix/__init__.py
pypartypix/jquery-latest.min.js
pypartypix/slideshow.html
pypartypix.egg-info/PKG-INFO
pypartypix.egg-info/SOURCES.txt
pypartypix.egg-info/dependency_links.txt
pypartypix.egg-info/entry_points.txt
pypartypix.egg-info/requires.txt
pypartypix.egg-info/top_level.txt
pypartypix/vegas/vegas.css
pypartypix/vegas/vegas.js