Metadata-Version: 1.1
Name: pypartypix
Version: 0.1.1
Summary: picture upload server for the included slideshow viewer
Home-page: https://github.com/JohnHouwer/pypartypix
Author: John Houwer
Author-email: john.houwer@gmail.com
License: MIT
Keywords: slideshow partypix picture upload
Platform: UNKNOWN
Classifier: Development Status :: 4 - Beta
Classifier: Intended Audience :: End Users/Desktop
Classifier: Environment :: Console
Classifier: Environment :: Web Environment
Classifier: Operating System :: POSIX
Classifier: Operating System :: Microsoft :: Windows
Classifier: Operating System :: MacOS
Classifier: License :: OSI Approved :: MIT License
Classifier: Programming Language :: Python :: 3
Classifier: Programming Language :: Python :: 3.2
Classifier: Programming Language :: Python :: 3.3
Classifier: Programming Language :: Python :: 3.4
Classifier: Programming Language :: JavaScript
Classifier: Topic :: Multimedia :: Graphics :: Presentation
